{
	"type": "create:crushing",
	"conditions": [
		{
			"type": "forge:mod_loaded",
			"modid": "create"
		}
	],
    "processsingTime": 250,
	"ingredients": [
		{
			"item": "sophies_alloys:quingum_deepslate_ore"
		}
	],
	"results": [
		{
			"item": "sophies_alloys:quingum_gem",
			"count": 2
		},
		{
			"chance": 0.75,
			"item": "sophies_alloys:quingum_gem"
		},
		{
			"chance": 0.75,
			"item": "create:experience_nugget"
		},
		{
			"chance": 0.125,
			"item": "minecraft:cobbled_deepslate"
		}
	]
}